gtk_stable_diffusion/__init__.py
gtk_stable_diffusion/ckpt_and_diffusers_mapping.py
gtk_stable_diffusion/ckpt_base.pt
gtk_stable_diffusion/ckpt_to_diffusers.py
gtk_stable_diffusion/ckpt_to_diffusers_read_list.py
gtk_stable_diffusion/convert_original_stable_diffusion_to_diffusers.py
gtk_stable_diffusion/danbooru_tags.py
gtk_stable_diffusion/deep_danbooru_model.py
gtk_stable_diffusion/free_weights.py
gtk_stable_diffusion/gtk_stable_diffusion.py
gtk_stable_diffusion/gtk_stable_diffusion_drawingarea_failed.py
gtk_stable_diffusion/gtk_stable_diffusion_gl.py
gtk_stable_diffusion/lpw_stable_diffusion.py
gtk_stable_diffusion/pkl_read.py
gtk_stable_diffusion/sd_prompt.lang
gtk_stable_diffusion/test.py
gtk_stable_diffusion/TorchDeepDanbooru/deep_danbooru_model.py
gtk_stable_diffusion/TorchDeepDanbooru/deep_danbooru_model_simple.py
gtk_stable_diffusion/TorchDeepDanbooru/inlined.py
gtk_stable_diffusion/TorchDeepDanbooru/inlined_constant.py
gtk_stable_diffusion/TorchDeepDanbooru/test.py
gtk_stable_diffusion-0.0.9.1.data/scripts/gtk-stable-diffusion
gtk_stable_diffusion-0.0.9.1.dist-info/LICENSE
gtk_stable_diffusion-0.0.9.1.dist-info/METADATA
gtk_stable_diffusion-0.0.9.1.dist-info/WHEEL
gtk_stable_diffusion-0.0.9.1.dist-info/top_level.txt
gtk_stable_diffusion-0.0.9.1.dist-info/RECORD
