Metadata-Version: 2.1
Name: gtk-stable-diffusion
Version: 0.0.9.1
Summary: A simple GTK UI for Stable Diffusion.
Home-page: https://github.com/nazodane/gtk_stable_diffusion
Author: Toshimitsu Kimura
Author-email: lovesyao@gmail.com
License: Apache
Keywords: stable_diffusion diffusers
Classifier: Development Status :: 3 - Alpha
Classifier: Topic :: Artistic Software
Classifier: License :: OSI Approved :: Apache Software License
Classifier: Programming Language :: Python :: 3.10
Classifier: Operating System :: POSIX :: Linux
Classifier: Environment :: GPU :: NVIDIA CUDA :: 11.7
Classifier: Intended Audience :: End Users/Desktop
Requires-Python: >=3.10.0
License-File: LICENSE
Requires-Dist: pycairo
Requires-Dist: PyGObject
Requires-Dist: torch
Requires-Dist: diffusers
Requires-Dist: numpy
Requires-Dist: xformers
Requires-Dist: libtorrent
Requires-Dist: omegaconf
Requires-Dist: toml
Requires-Dist: nltk
